ollama_mcp_bridge/__init__.py
ollama_mcp_bridge/_version.py
ollama_mcp_bridge/api.py
ollama_mcp_bridge/lifecycle.py
ollama_mcp_bridge/main.py
ollama_mcp_bridge/mcp_manager.py
ollama_mcp_bridge/proxy_service.py
ollama_mcp_bridge/schemas.py
ollama_mcp_bridge/utils.py
ollama_mcp_bridge-0.9.2.dist-info/METADATA
ollama_mcp_bridge-0.9.2.dist-info/WHEEL
ollama_mcp_bridge-0.9.2.dist-info/entry_points.txt
ollama_mcp_bridge-0.9.2.dist-info/licenses/LICENSE
ollama_mcp_bridge-0.9.2.dist-info/RECORD
