Metadata-Version: 2.4
Name: ollama-mcp-bridge
Version: 0.9.2
Summary: Bridge API service connecting Ollama with Model Context Protocol (MCP) servers
Project-URL: Documentation, https://github.com/jonigl/ollama-mcp-bridge#readme
Project-URL: Issues, https://github.com/jonigl/ollama-mcp-bridge/issues
Project-URL: Source, https://github.com/jonigl/ollama-mcp-bridge
Author: Jonathan Gastón Löwenstern
License-Expression: MIT
License-File: LICENSE
Keywords: ai,api,bridge,fastapi,llm,local-llm,mcp,model-context-protocol,ollama,ollama-api,ollama-mcp,proxy,tools
Requires-Python: >=3.10
Requires-Dist: fastapi~=0.119.0
Requires-Dist: httpx~=0.28.0
Requires-Dist: loguru~=0.7.3
Requires-Dist: mcp<2.0.0,>=1.9.4
Requires-Dist: packaging>=25.0
Requires-Dist: typer~=0.20.0
Requires-Dist: uvicorn~=0.38.0
